<?xml version="1.0" encoding="UTF-8" standalone="yes"?><ns0:RetrieveMultipleValueSetsResponse xmlns:ns0="urn:ihe:iti:svs:2008" xmlns:xsi="http://www.w3.org/2001/XMLSchema-instance">    <ns0:DescribedValueSet ID="2.16.840.1.113762.1.4.1116.365" displayName="Hospice Care Referral or Admission" version="N/A">        <ns0:ConceptList>            <ns0:Concept code="183919006" codeSystem="2.16.840.1.113883.6.96" codeSystemName="SNOMEDCT" codeSystemVersion="2019-09" displayName="Urgent admission to hospice (procedure)"/>            <ns0:Concept code="183920000" codeSystem="2.16.840.1.113883.6.96" codeSystemName="SNOMEDCT" codeSystemVersion="2019-09" displayName="Routine admission to hospice (procedure)"/>            <ns0:Concept code="183921001" codeSystem="2.16.840.1.113883.6.96" codeSystemName="SNOMEDCT" codeSystemVersion="2019-09" displayName="Admission to hospice for respite (procedure)"/>            <ns0:Concept code="305336008" codeSystem="2.16.840.1.113883.6.96" codeSystemName="SNOMEDCT" codeSystemVersion="2019-09" displayName="Admission to hospice (procedure)"/>            <ns0:Concept code="306205009" codeSystem="2.16.840.1.113883.6.96" codeSystemName="SNOMEDCT" codeSystemVersion="2019-09" displayName="Referral to hospice (procedure)"/>            <ns0:Concept code="385765002" codeSystem="2.16.840.1.113883.6.96" codeSystemName="SNOMEDCT" codeSystemVersion="2019-09" displayName="Hospice care management (procedure)"/>            <ns0:Concept code="428361000124107" codeSystem="2.16.840.1.113883.6.96" codeSystemName="SNOMEDCT" codeSystemVersion="2019-09" displayName="Discharge to home for hospice care (procedure)"/>            <ns0:Concept code="428371000124100" codeSystem="2.16.840.1.113883.6.96" codeSystemName="SNOMEDCT" codeSystemVersion="2019-09" displayName="Discharge to healthcare facility for hospice care (procedure)"/>            <ns0:Concept code="444933003" codeSystem="2.16.840.1.113883.6.96" codeSystemName="SNOMEDCT" codeSystemVersion="2019-09" displayName="Home hospice service (qualifier value)"/>        </ns0:ConceptList>        <ns0:Source>American Society of Clinical Oncology</ns0:Source>        <ns0:Purpose>(Clinical Focus: ),(Data Element Scope: ),(Inclusion Criteria: ),(Exclusion Criteria: )</ns0:Purpose>        <ns0:Type>Extensional</ns0:Type>        <ns0:Binding>Dynamic</ns0:Binding>        <ns0:Status>Active</ns0:Status>        <ns0:RevisionDate>2019-10-10</ns0:RevisionDate>    </ns0:DescribedValueSet></ns0:RetrieveMultipleValueSetsResponse>