<?xml version="1.0" encoding="UTF-8" standalone="yes"?><ns0:RetrieveMultipleValueSetsResponse xmlns:ns0="urn:ihe:iti:svs:2008" xmlns:xsi="http://www.w3.org/2001/XMLSchema-instance">    <ns0:DescribedValueSet ID="2.16.840.1.113762.1.4.1116.339" displayName="Radiation Therapy Encounter" version="N/A">        <ns0:ConceptList>            <ns0:Concept code="77427" codeSystem="2.16.840.1.113883.6.12" codeSystemName="CPT" codeSystemVersion="2019" displayName="Radiation treatment management, 5 treatments"/>            <ns0:Concept code="77435" codeSystem="2.16.840.1.113883.6.12" codeSystemName="CPT" codeSystemVersion="2019" displayName="Stereotactic body radiation therapy, treatment management, per treatment course, to 1 or more lesions, including image guidance, entire course not to exceed 5 fractions"/>        </ns0:ConceptList>        <ns0:Source>American Society of Clinical Oncology</ns0:Source>        <ns0:Purpose>(Clinical Focus: ),(Data Element Scope: ),(Inclusion Criteria: ),(Exclusion Criteria: )</ns0:Purpose>        <ns0:Type>Extensional</ns0:Type>        <ns0:Binding>Dynamic</ns0:Binding>        <ns0:Status>Active</ns0:Status>        <ns0:RevisionDate>2017-04-29</ns0:RevisionDate>    </ns0:DescribedValueSet></ns0:RetrieveMultipleValueSetsResponse>