<?xml version="1.0" encoding="UTF-8" standalone="yes"?><ns0:RetrieveMultipleValueSetsResponse xmlns:ns0="urn:ihe:iti:svs:2008" xmlns:xsi="http://www.w3.org/2001/XMLSchema-instance">    <ns0:DescribedValueSet ID="2.16.840.1.113762.1.4.1204.23" displayName="Pain Scale" version="N/A">        <ns0:ConceptList>            <ns0:Concept code="38208-5" codeSystem="2.16.840.1.113883.6.1" codeSystemName="LOINC" codeSystemVersion="2.66" displayName="Pain severity - Reported"/>            <ns0:Concept code="38214-3" codeSystem="2.16.840.1.113883.6.1" codeSystemName="LOINC" codeSystemVersion="2.66" displayName="Pain severity [Score] Visual analog score"/>            <ns0:Concept code="38215-0" codeSystem="2.16.840.1.113883.6.1" codeSystemName="LOINC" codeSystemVersion="2.66" displayName="Pain severity total [Score] FLACC"/>            <ns0:Concept code="38216-8" codeSystem="2.16.840.1.113883.6.1" codeSystemName="LOINC" codeSystemVersion="2.66" displayName="Pain severity Face FLACC"/>            <ns0:Concept code="38217-6" codeSystem="2.16.840.1.113883.6.1" codeSystemName="LOINC" codeSystemVersion="2.66" displayName="Pain severity Legs FLACC"/>            <ns0:Concept code="38218-4" codeSystem="2.16.840.1.113883.6.1" codeSystemName="LOINC" codeSystemVersion="2.66" displayName="Pain severity Activity FLACC"/>            <ns0:Concept code="38219-2" codeSystem="2.16.840.1.113883.6.1" codeSystemName="LOINC" codeSystemVersion="2.66" displayName="Pain severity Cry FLACC"/>            <ns0:Concept code="38220-0" codeSystem="2.16.840.1.113883.6.1" codeSystemName="LOINC" codeSystemVersion="2.66" displayName="Pain severity Consolability FLACC"/>            <ns0:Concept code="38221-8" codeSystem="2.16.840.1.113883.6.1" codeSystemName="LOINC" codeSystemVersion="2.66" displayName="Pain severity Wong-Baker FACES pain rating scale"/>            <ns0:Concept code="56840-2" codeSystem="2.16.840.1.113883.6.1" codeSystemName="LOINC" codeSystemVersion="2.66" displayName="Pain severity verbal numeric scale [Score]"/>            <ns0:Concept code="56841-0" codeSystem="2.16.840.1.113883.6.1" codeSystemName="LOINC" codeSystemVersion="2.66" displayName="Pain severity descriptive category"/>            <ns0:Concept code="57696-7" codeSystem="2.16.840.1.113883.6.1" codeSystemName="LOINC" codeSystemVersion="2.66" displayName="Pain severity FPS-R"/>            <ns0:Concept code="64008-6" codeSystem="2.16.840.1.113883.6.1" codeSystemName="LOINC" codeSystemVersion="2.66" displayName="Pain severity [Score] [PhenX]"/>            <ns0:Concept code="72514-3" codeSystem="2.16.840.1.113883.6.1" codeSystemName="LOINC" codeSystemVersion="2.66" displayName="Pain severity - 0-10 verbal numeric rating [Score] - Reported"/>            <ns0:Concept code="75893-8" codeSystem="2.16.840.1.113883.6.1" codeSystemName="LOINC" codeSystemVersion="2.66" displayName="Pain severity in the past week - 0-10 numeric rating [Reported]"/>            <ns0:Concept code="LA12187-3" codeSystem="2.16.840.1.113883.6.1" codeSystemName="LOINC" codeSystemVersion="2.66" displayName="Yes, and it does not indicate severe pain"/>            <ns0:Concept code="LA12188-1" codeSystem="2.16.840.1.113883.6.1" codeSystemName="LOINC" codeSystemVersion="2.66" displayName="Yes, and it indicates severe pain"/>            <ns0:Concept code="LA15108-6" codeSystem="2.16.840.1.113883.6.1" codeSystemName="LOINC" codeSystemVersion="2.66" displayName="Extremely severe pain"/>            <ns0:Concept code="LA15109-4" codeSystem="2.16.840.1.113883.6.1" codeSystemName="LOINC" codeSystemVersion="2.66" displayName="Severe pain"/>            <ns0:Concept code="LA15110-2" codeSystem="2.16.840.1.113883.6.1" codeSystemName="LOINC" codeSystemVersion="2.66" displayName="Moderately severe pain"/>            <ns0:Concept code="LA21630-1" codeSystem="2.16.840.1.113883.6.1" codeSystemName="LOINC" codeSystemVersion="2.66" displayName="10 - Severe pain"/>            <ns0:Concept code="LA25253-8" codeSystem="2.16.840.1.113883.6.1" codeSystemName="LOINC" codeSystemVersion="2.66" displayName="Pain severity 0-10"/>            <ns0:Concept code="LA25856-8" codeSystem="2.16.840.1.113883.6.1" codeSystemName="LOINC" codeSystemVersion="2.66" displayName="The pain is fairly severe at the moment."/>            <ns0:Concept code="LP157783-4" codeSystem="2.16.840.1.113883.6.1" codeSystemName="LOINC" codeSystemVersion="2.66" displayName="Pain severity - 0-10 verbal numeric rating"/>            <ns0:Concept code="LP34350-6" codeSystem="2.16.840.1.113883.6.1" codeSystemName="LOINC" codeSystemVersion="2.66" displayName="Pain severity"/>            <ns0:Concept code="LP96291-7" codeSystem="2.16.840.1.113883.6.1" codeSystemName="LOINC" codeSystemVersion="2.66" displayName="Pain severity verbal numeric scale"/>            <ns0:Concept code="LP96292-5" codeSystem="2.16.840.1.113883.6.1" codeSystemName="LOINC" codeSystemVersion="2.66" displayName="Pain severity descriptive category"/>        </ns0:ConceptList>        <ns0:Source>National EMS Quality Alliance</ns0:Source>        <ns0:Purpose>(Clinical Focus: This set of values contains assessments that are used to measure pain levels for patients, particularly those who are injured.),(Data Element Scope: The intent of this data element is to identify patients whose pain was assessed using a pain scale. Using the Quality Data Model, this particular element would map to the "Assessment" category.),(Inclusion Criteria: Pain assessment scales for both pediatric and adult patients should be included.),(Exclusion Criteria: None)</ns0:Purpose>        <ns0:Type>Extensional</ns0:Type>        <ns0:Binding>Dynamic</ns0:Binding>        <ns0:Status>Active</ns0:Status>        <ns0:RevisionDate>2019-05-24</ns0:RevisionDate>    </ns0:DescribedValueSet></ns0:RetrieveMultipleValueSetsResponse>