<?xml version="1.0" encoding="UTF-8" standalone="yes"?><ns0:RetrieveMultipleValueSetsResponse xmlns:ns0="urn:ihe:iti:svs:2008" xmlns:xsi="http://www.w3.org/2001/XMLSchema-instance">    <ns0:DescribedValueSet ID="2.16.840.1.113762.1.4.1116.76" displayName="Procedure intent documented" version="N/A">        <ns0:ConceptList>            <ns0:Concept code="129428001" codeSystem="2.16.840.1.113883.6.96" codeSystemName="SNOMEDCT" codeSystemVersion="2019-09" displayName="Preventive - procedure intent (qualifier value)"/>            <ns0:Concept code="134410009" codeSystem="2.16.840.1.113883.6.96" codeSystemName="SNOMEDCT" codeSystemVersion="2019-09" displayName="Maintenance stage (qualifier value)"/>            <ns0:Concept code="246106000" codeSystem="2.16.840.1.113883.6.96" codeSystemName="SNOMEDCT" codeSystemVersion="2019-09" displayName="Control (attribute)"/>            <ns0:Concept code="255595002" codeSystem="2.16.840.1.113883.6.96" codeSystemName="SNOMEDCT" codeSystemVersion="2019-09" displayName="Debulking - action (qualifier value)"/>            <ns0:Concept code="261002007" codeSystem="2.16.840.1.113883.6.96" codeSystemName="SNOMEDCT" codeSystemVersion="2019-09" displayName="Definitive (qualifier value)"/>            <ns0:Concept code="262202000" codeSystem="2.16.840.1.113883.6.96" codeSystemName="SNOMEDCT" codeSystemVersion="2019-09" displayName="Therapeutic intent (qualifier value)"/>            <ns0:Concept code="277022003" codeSystem="2.16.840.1.113883.6.96" codeSystemName="SNOMEDCT" codeSystemVersion="2019-09" displayName="Remission phase (qualifier value)"/>            <ns0:Concept code="360161008" codeSystem="2.16.840.1.113883.6.96" codeSystemName="SNOMEDCT" codeSystemVersion="2019-09" displayName="Induction - action (qualifier value)"/>            <ns0:Concept code="363676003" codeSystem="2.16.840.1.113883.6.96" codeSystemName="SNOMEDCT" codeSystemVersion="2019-09" displayName="Palliative - procedure intent (qualifier value)"/>            <ns0:Concept code="373808002" codeSystem="2.16.840.1.113883.6.96" codeSystemName="SNOMEDCT" codeSystemVersion="2019-09" displayName="Curative - procedure intent (qualifier value)"/>            <ns0:Concept code="373846009" codeSystem="2.16.840.1.113883.6.96" codeSystemName="SNOMEDCT" codeSystemVersion="2019-09" displayName="Adjuvant - intent (qualifier value)"/>            <ns0:Concept code="373847000" codeSystem="2.16.840.1.113883.6.96" codeSystemName="SNOMEDCT" codeSystemVersion="2019-09" displayName="Neo-adjuvant - intent (qualifier value)"/>            <ns0:Concept code="385432009" codeSystem="2.16.840.1.113883.6.96" codeSystemName="SNOMEDCT" codeSystemVersion="2019-09" displayName="Not applicable (qualifier value)"/>            <ns0:Concept code="399707004" codeSystem="2.16.840.1.113883.6.96" codeSystemName="SNOMEDCT" codeSystemVersion="2019-09" displayName="Supportive - procedure intent (qualifier value)"/>            <ns0:Concept code="445150007" codeSystem="2.16.840.1.113883.6.96" codeSystemName="SNOMEDCT" codeSystemVersion="2019-09" displayName="Surviving free of recurrence of neoplastic disease (finding)"/>            <ns0:Concept code="52052004" codeSystem="2.16.840.1.113883.6.96" codeSystemName="SNOMEDCT" codeSystemVersion="2019-09" displayName="Rehabilitation therapy (regime/therapy)"/>            <ns0:Concept code="74964007" codeSystem="2.16.840.1.113883.6.96" codeSystemName="SNOMEDCT" codeSystemVersion="2019-09" displayName="Other (qualifier value)"/>        </ns0:ConceptList>        <ns0:Source>American Society of Clinical Oncology</ns0:Source>        <ns0:Purpose>(Clinical Focus: ),(Data Element Scope: ),(Inclusion Criteria: ),(Exclusion Criteria: )</ns0:Purpose>        <ns0:Type>Extensional</ns0:Type>        <ns0:Binding>Dynamic</ns0:Binding>        <ns0:Status>Active</ns0:Status>        <ns0:RevisionDate>2018-08-29</ns0:RevisionDate>    </ns0:DescribedValueSet></ns0:RetrieveMultipleValueSetsResponse>