<?xml version="1.0" encoding="UTF-8" standalone="yes"?><ns0:RetrieveMultipleValueSetsResponse xmlns:ns0="urn:ihe:iti:svs:2008" xmlns:xsi="http://www.w3.org/2001/XMLSchema-instance">    <ns0:DescribedValueSet ID="2.16.840.1.113883.3.3157.1004.18" displayName="Tramadol" version="N/A">        <ns0:ConceptList>            <ns0:Concept code="1148478" codeSystem="2.16.840.1.113883.6.88" codeSystemName="RXNORM" codeSystemVersion="2019-10" displayName="24 HR tramadol hydrochloride 100 MG Extended Release Oral Capsule"/>            <ns0:Concept code="1148485" codeSystem="2.16.840.1.113883.6.88" codeSystemName="RXNORM" codeSystemVersion="2019-10" displayName="24 HR tramadol hydrochloride 200 MG Extended Release Oral Capsule"/>            <ns0:Concept code="1148489" codeSystem="2.16.840.1.113883.6.88" codeSystemName="RXNORM" codeSystemVersion="2019-10" displayName="24 HR tramadol hydrochloride 300 MG Extended Release Oral Capsule"/>            <ns0:Concept code="1248115" codeSystem="2.16.840.1.113883.6.88" codeSystemName="RXNORM" codeSystemVersion="2019-10" displayName="24 HR tramadol hydrochloride 150 MG Extended Release Oral Capsule"/>            <ns0:Concept code="1946525" codeSystem="2.16.840.1.113883.6.88" codeSystemName="RXNORM" codeSystemVersion="2019-10" displayName="Matrix Delivery 24 HR tramadol hydrochloride 300 MG Extended Release Oral Tablet"/>            <ns0:Concept code="1946527" codeSystem="2.16.840.1.113883.6.88" codeSystemName="RXNORM" codeSystemVersion="2019-10" displayName="Matrix Delivery 24 HR tramadol hydrochloride 200 MG Extended Release Oral Tablet"/>            <ns0:Concept code="1946529" codeSystem="2.16.840.1.113883.6.88" codeSystemName="RXNORM" codeSystemVersion="2019-10" displayName="Matrix Delivery 24 HR tramadol hydrochloride 100 MG Extended Release Oral Tablet"/>            <ns0:Concept code="833709" codeSystem="2.16.840.1.113883.6.88" codeSystemName="RXNORM" codeSystemVersion="2019-10" displayName="24 HR tramadol hydrochloride 100 MG Extended Release Oral Tablet"/>            <ns0:Concept code="833711" codeSystem="2.16.840.1.113883.6.88" codeSystemName="RXNORM" codeSystemVersion="2019-10" displayName="24 HR tramadol hydrochloride 200 MG Extended Release Oral Tablet"/>            <ns0:Concept code="833713" codeSystem="2.16.840.1.113883.6.88" codeSystemName="RXNORM" codeSystemVersion="2019-10" displayName="24 HR tramadol hydrochloride 300 MG Extended Release Oral Tablet"/>            <ns0:Concept code="835603" codeSystem="2.16.840.1.113883.6.88" codeSystemName="RXNORM" codeSystemVersion="2019-10" displayName="tramadol hydrochloride 50 MG Oral Tablet"/>            <ns0:Concept code="836395" codeSystem="2.16.840.1.113883.6.88" codeSystemName="RXNORM" codeSystemVersion="2019-10" displayName="Acetaminophen 325 MG / tramadol hydrochloride 37.5 MG Oral Tablet"/>        </ns0:ConceptList>        <ns0:Source>Mathematica</ns0:Source>        <ns0:Purpose>(Clinical Focus: This set of RxNorm codes is intended to capture orders of any medication containing tramadol.),(Data Element Scope: The intent of this data element is to identify patients who are prescribed tramadol.),(Inclusion Criteria: RxNorm codes associated with tramadol are included in the value set.),(Exclusion Criteria: Medications without tramadol are excluded from the value set.)</ns0:Purpose>        <ns0:Type>Extensional</ns0:Type>        <ns0:Binding>Dynamic</ns0:Binding>        <ns0:Status>Active</ns0:Status>        <ns0:RevisionDate>2019-03-16</ns0:RevisionDate>    </ns0:DescribedValueSet></ns0:RetrieveMultipleValueSetsResponse>